tests/__init__.py
tests/testApp.py
tests/testCommunity.py
tests/testInvitation.py
tests/testNode.py
tests/testUser.py
tests/tests.py
tests/app/__init__.py
tests/app/app.py
tests/app/config.py
tests/app/models.py
ySanic/__init__.py
ySanic-0.1.0.dist-info/LICENSE
ySanic-0.1.0.dist-info/METADATA
ySanic-0.1.0.dist-info/WHEEL
ySanic-0.1.0.dist-info/dependency_links.txt
ySanic-0.1.0.dist-info/top_level.txt
ySanic-0.1.0.dist-info/RECORD
