Metadata-Version: 2.1
Name: ySanic
Version: 0.1.0
Summary: ySanic subclass with some addons to sanic
Home-page: https://github.com/Garito/ySanic
Author: Garito
Author-email: garito@gmail.com
License: MIT
Keywords: sanic
Platform: UNKNOWN
Classifier: Development Status :: 4 - Beta
Classifier: Environment :: Plugins
Classifier: Intended Audience :: Developers
Classifier: License :: OSI Approved :: MIT License
Classifier: Programming Language :: Python :: 3
Classifier: Topic :: Internet :: WWW/HTTP :: WSGI :: Server
Requires-Python: >=3.6
Requires-Dist: sanic
Requires-Dist: yModel
